dbtmon/__init__.py
dbtmon/__main__.py
dbtmon/config.py
dbtmon/monitor.py
dbtmon-1.1.9.dist-info/licenses/LICENSE
dbtmon-1.1.9.dist-info/METADATA
dbtmon-1.1.9.dist-info/WHEEL
dbtmon-1.1.9.dist-info/entry_points.txt
dbtmon-1.1.9.dist-info/top_level.txt
dbtmon-1.1.9.dist-info/RECORD
