Metadata-Version: 2.4
Name: dbtmon
Version: 1.1.9
Summary: A simple wrapper program for modifying dbt command output
Author-email: John Small <johnsmall407@gmail.com>
License-Expression: Apache-2.0
Project-URL: Homepage, https://github.com/Southern-Sun/dbtmon
Project-URL: Bug Tracker, https://github.com/Southern-Sun/dbtmon/issues
Classifier: Programming Language :: Python :: 3
Classifier: Operating System :: OS Independent
Requires-Python: >=3.10.11
License-File: LICENSE
Dynamic: license-file
